{
  "model": {
    "type": "minecraft:range_dispatch",
    "property": "minecraft:custom_model_data",
    "fallback": {
      "type": "minecraft:model",
      "model": "minecraft:item/netherite_sword"
    },
    "entries": [
      {"threshold": 1001, "model": {"type": "minecraft:model", "model": "weapons/arc3/pure_blade"}},
      {"threshold": 1002, "model": {"type": "minecraft:model", "model": "weapons/arc3/dagger"}},
      {"threshold": 1003, "model": {"type": "minecraft:model", "model": "weapons/arc3/wind"}},
      {"threshold": 1004, "model": {"type": "minecraft:model", "model": "weapons/arc3/cutlass"}},
      {"threshold": 1005, "model": {"type": "minecraft:model", "model": "weapons/bloodlust"}},
      {"threshold": 1006, "model": {"type": "minecraft:model", "model": "weapons/arc5/sculk"}},
      {"threshold": 1007, "model": {"type": "minecraft:model", "model": "weapons/arc3/gauntlet"}},
      {"threshold": 1008, "model": {"type": "minecraft:model", "model": "weapons/frost"}},
      {"threshold": 1009, "model": {"type": "minecraft:model", "model": "weapons/hyperion"}},
      {"threshold": 1010, "model": {"type": "minecraft:model", "model": "weapons/arc3/cutlass"}},
      {"threshold": 1011, "model": {"type": "minecraft:model", "model": "weapons/arc5/eclipse"}},
      {"threshold": 1012, "model": {"type": "minecraft:model", "model": "weapons/arc3/pure_blade"}},
      {"threshold": 1013, "model": {"type": "minecraft:model", "model": "weapons/illusion_wand"}},
      {"threshold": 1014, "model": {"type": "minecraft:model", "model": "weapons/bone_blade"}},
      {"threshold": 1015, "model": {"type": "minecraft:model", "model": "weapons/arc5/mace/lv3"}},
      {"threshold": 1016, "model": {"type": "minecraft:model", "model": "weapons/arc3/witherbone"}},
      {"threshold": 1017, "model": {"type": "minecraft:model", "model": "weapons/arc3/dagger"}},
      {"threshold": 1018, "model": {"type": "minecraft:model", "model": "custom/vampire"}},
      {"threshold": 1019, "model": {"type": "minecraft:model", "model": "weapons/arc5/nukeremote"}},
      {"threshold": 1020, "model": {"type": "minecraft:model", "model": "weapons/arc3/axe"}},
      {"threshold": 1021, "model": {"type": "minecraft:model", "model": "weapons/arc5/mace/lv2"}},
      {"threshold": 1022, "model": {"type": "minecraft:model", "model": "weapons/arc5/mace/lv1"}},
      {"threshold": 1023, "model": {"type": "minecraft:model", "model": "custom/pale"}},
      {"threshold": 1024, "model": {"type": "minecraft:model", "model": "weapons/illusion_wand"}},
      {"threshold": 1025, "model": {"type": "minecraft:model", "model": "weapons/arc3/wind"}}
    ]
  }
}
